adslproxy/__init__.py
adslproxy/__version__.py
adslproxy/cmd.py
adslproxy/db.py
adslproxy/settings.py
adslproxy/checker/__init__.py
adslproxy/checker/checker.py
adslproxy/sender/__init__.py
adslproxy/sender/sender.py
adslproxy/server/__init__.py
adslproxy/server/server.py
adslproxy_enhance-3.5.0.dist-info/LICENSE
adslproxy_enhance-3.5.0.dist-info/METADATA
adslproxy_enhance-3.5.0.dist-info/WHEEL
adslproxy_enhance-3.5.0.dist-info/entry_points.txt
adslproxy_enhance-3.5.0.dist-info/top_level.txt
adslproxy_enhance-3.5.0.dist-info/RECORD
