Metadata-Version: 2.1
Name: adslproxy-enhance
Version: 3.5.0
Summary: ADSL Proxy Pool Tool 
Home-page: https://github.com/thefantasystudio/AdslProxy
Author: Germey
Author-email: cqc@cuiqingcai.com
License: MIT
Platform: UNKNOWN
Classifier: License :: OSI Approved :: MIT License
Classifier: Programming Language :: Python :: 3.5
Classifier: Programming Language :: Python :: 3.6
Classifier: Programming Language :: Python :: 3.7
Classifier: Programming Language :: Python :: Implementation :: CPython
Classifier: Programming Language :: Python :: Implementation :: PyPy
Requires-Python: >=3.5.0
License-File: LICENSE
Requires-Dist: requests
Requires-Dist: redis (==2.10.5)
Requires-Dist: tornado
Requires-Dist: environs
Requires-Dist: loguru
Requires-Dist: retrying
